track_flow/__init__.py
track_flow/main.py
track_flow/DTO/__init__.py
track_flow/DTO/dto.py
track_flow/contracts/__init__.py
track_flow/contracts/extractor.py
track_flow/contracts/loader.py
track_flow/contracts/trasformer.py
track_flow/extract/__init__.py
track_flow/extract/extract.py
track_flow/load/__init__.py
track_flow/load/load.py
track_flow/transform/__init__.py
track_flow/transform/transform.py
track_flow/utils/__init__.py
track_flow/utils/file_manager.py
track_flow-0.1.9.dist-info/licenses/LICENSE
track_flow-0.1.9.dist-info/METADATA
track_flow-0.1.9.dist-info/WHEEL
track_flow-0.1.9.dist-info/entry_points.txt
track_flow-0.1.9.dist-info/top_level.txt
track_flow-0.1.9.dist-info/RECORD
