Metadata-Version: 2.4
Name: track-flow
Version: 0.1.9
Summary: ETL para extraer, transformar y cargar datos de charts de spotify en S3
Home-page: https://github.com/facuvegaingenieer/track-flow
Author: Walter Facundo Vega
Author-email: facundo.vega1234@gmail.com
License: MIT
Classifier: Programming Language :: Python :: 3
Classifier: Programming Language :: Python :: 3.8
Classifier: License :: OSI Approved :: MIT License
Classifier: Operating System :: OS Independent
Requires-Python: >=3.8
License-File: LICENSE
Requires-Dist: pandas
Requires-Dist: boto3
Requires-Dist: pyarrow
Requires-Dist: python-dotenv
Requires-Dist: requests
Dynamic: author
Dynamic: author-email
Dynamic: classifier
Dynamic: description
Dynamic: description-content-type
Dynamic: home-page
Dynamic: license
Dynamic: license-file
Dynamic: requires-dist
Dynamic: requires-python
Dynamic: summary
